pikax/__init__.py
pikax/downloader.py
pikax/exceptions.py
pikax/items.py
pikax/models.py
pikax/params.py
pikax/pikax.py
pikax/processor.py
pikax/result.py
pikax/settings.py
pikax/texts.py
pikax/user.py
pikax/util.py
pikax/api/__init__.py
pikax/api/androidclient.py
pikax/api/artwork.py
pikax/api/defaultclient.py
pikax/api/models.py
pikax/api/webclient.py
pikax-2.2.7.dist-info/LICENSE
pikax-2.2.7.dist-info/METADATA
pikax-2.2.7.dist-info/WHEEL
pikax-2.2.7.dist-info/top_level.txt
pikax-2.2.7.dist-info/RECORD
