Metadata-Version: 2.1
Name: pikax
Version: 2.2.7
Summary: A Pixiv Mass Downloading Tool
Home-page: https://github.com/Redcxx/Pikax
Author: Redcxx
Author-email: weilue.luo@student.manchester.ac.uk
License: UNKNOWN
Platform: UNKNOWN
Classifier: Programming Language :: Python :: 3
Classifier: License :: OSI Approved :: BSD License
Classifier: Operating System :: Microsoft :: Windows :: Windows 10
Classifier: Topic :: Utilities
Requires-Dist: requests
